fastbzip2/__init__.py
fastbzip2/fastbzip2_lib.abi3.h
fastbzip2/fastbzip2_lib.abi3.so
fastbzip2_lib-0.2.dist-info/METADATA
fastbzip2_lib-0.2.dist-info/WHEEL
fastbzip2_lib-0.2.dist-info/top_level.txt
fastbzip2_lib-0.2.dist-info/RECORD
