Metadata-Version: 2.1
Name: fastbzip2_lib
Version: 0.2
Summary: Parallel BZIP2 Decompression
Author: Hugo Pendlebury
